opentranslator/__init__.py
opentranslator/app.py
opentranslator/version.py
opentranslator-0.0.1.data/scripts/opentranslator
opentranslator-0.0.1.dist-info/LICENSE
opentranslator-0.0.1.dist-info/METADATA
opentranslator-0.0.1.dist-info/WHEEL
opentranslator-0.0.1.dist-info/top_level.txt
opentranslator-0.0.1.dist-info/RECORD
