Metadata-Version: 2.1
Name: opentranslator
Version: 0.0.1
Summary: Python client library for translate text with OpenAI API
Home-page: https://github.com/fabriziocafolla/opentranslator
Author: FabrizioCafolla
Author-email: developer@fabriziocafolla.com
License: UNKNOWN
Platform: UNKNOWN
Requires-Python: >=3.7
Requires-Dist: click (>=8.*)
Requires-Dist: openai
